{
	"cv": {
		"basic_info": {
			"first_name": "Nikola",
			"id": "b63926ee-87ae-45c9-be84-98d4dd9b2f51",
			"last_name": "Vrhovac",
			"title": "Front-end developer"
		},
		"contact": {
			"category": "aside",
			"content": {
				"data": {
					"address": "Wien, Austria",
					"e_mail": "nikola@return.rs",
					"phone": "+43 676 6472875"
				},
				"type": "titlelist"
			},
			"id": "f75f44f0-f6d5-49b1-ac62-ff2fd2cacab5",
			"title": "Contact",
			"type": "contact"
		},
		"education": {
			"category": "main",
			"content": [
				{
					"description": "Master of Architecture",
					"id": "930aa0b4-b973-45c9-b7b0-0192ce4be937",
					"name": "University of Belgrade - Faculty of Architecture",
					"specialization": "Bioclimatic architecture",
					"time_end": "2012",
					"time_start": "2000",
					"title": "Architectural engineer",
					"url": "http://www.arh.bg.ac.rs/en/"
				},
				{
					"description": "Applied sciences and mathematics",
					"id": "064333fd-2072-4823-bc7a-f8f8978330ad",
					"time_end": "2000",
					"time_start": "1996",
					"title": "XV Belgrade Gymnasium",
					"url": "https://gimnazijapatrijarhpavle.edu.rs/"
				}
			],
			"id": "24ea3000-4688-4c1f-8997-486f7c67bcb8",
			"title": "Education",
			"type": "education"
		},
		"experience": {
			"category": "main",
			"content": [
				{
					"id": "05b66e54-f02f-4938-83b4-00c2750b0438",
					"company": "BWIN (Entain)",
					"description": "Entain plc (LSE: ENT) is the FTSE 100 company that is one of the world’s largest sports betting and gaming groups operating in the online and retail sector.",
					"job_title": "Front-end developer",
					"responsibilities": [
						"maintenance and improvement of a scalable in house developed web frontend framework which is used by all Entain’s customer-facing websites",
						"bwin.com, ladbrokes.com, coral.co.uk, sportingbet.com, partypoker.com... many more"
					],
					"technologies": [
						"angular",
						"typescript",
						"css3",
						"gulp",
						"sass",
						"webpack",
						".NET",
						"sitecore"
					],
					"time_end": "present",
					"time_start": "Dec 2019"
				},
				{
					"company": "Gowi DOO",
					"examples": [
						{
							"title": "beacon-intelligence.com"
						},
						{
							"title": "structuredretailproducts.com",
							"url": "https://www.structuredretailproducts.com/"
						},
						{
							"title": "insuranceinsider.com",
							"url": "https://www.insuranceinsider.com/"
						},
						{
							"title": "trading-risk.com",
							"url": "https://www.trading-risk.com/"
						}
					],
					"id": "b779f361-50a6-48af-a559-758317cd6da2",
					"job_title": "Front-end developer",
					"responsibilities": [
						"redux, webpack, authorization, front-end architecture planning and app lifecycle setup",
						"creating angularjs, react or pure HTML, CSS, jquery front-end apps from ground up"
					],
					"technologies": [
						"react",
						"redux",
						"angular",
						"typescript",
						"sass",
						"less",
						"css3",
						"gulp",
						"jquery",
						"webpack",
						".NET",
						"sitecore"
					],
					"time_end": "Dec 2019",
					"time_start": "May 2017"
				},
				{
					"company": "Civic initiatives",
					"description": "Nonprofit organization with a mission to strengthen civil society through education, promotion of democracy and support of active citizenship.",
					"examples": [
						{
							"title": "gradjanske.org",
							"url": "https://www.gradjanske.org/"
						},
						{
							"title": "rc.gradjanske.org",
							"url": "https://rc.gradjanske.org/"
						},
						{
							"title": "vodic.gradjanske.org",
							"url": "https://vodic.gradjanske.org/"
						},
						{
							"title": "mireditadobardan.com",
							"url": "https://mireditadobardan.com/"
						},
						{
							"title": "udruzenja.info",
							"url": "https://udruzenja.info/"
						},
						{
							"title": "udruzeni.org"
						},
						{
							"title": "sekomehanizam.org",
							"url": "http://sekomehanizam.org/"
						}
					],
					"id": "78c2b027-30bb-4983-8b74-300245eb41e4",
					"job_title": "Developer Consultant",
					"responsibilities": [
						"more then ten wordpress pages, apache servers, setup, migrations, security, optimization, backups",
						"design and layouts, themes, front-end, SEO, analytics",
						"project tech planning and development"
					],
					"technologies": [
						"php",
						"wordpress",
						"javascript",
						"jquery",
						"wp rest api",
						"css",
						"html"
					],
					"time_end": "Dec 2019",
					"time_start": "Sep 2016"
				},
				{
					"additional_info": "Cookpad Inc. startup (cookpad.jp)",
					"company": "Farmstand",
					"description": "Farmdoor is a 24/7 farmers market stand on the streets of Palo Alto. Customers were offered to buy fresh fruits and vegetables from self-serving stands using web and phone app.",
					"examples": [
						{
							"title": "farmdoor.me"
						}
					],
					"id": "a6b3b07f-31ef-4d87-b502-7bd0f5d1be19",
					"job_title": "Technical project coordinator",
					"responsibilities": [
						"developer team assistance, coordination and planning",
						"transactional and newsletter email development",
						"project time-frames, scheduling, graphs and analysis"
					],
					"technologies": [
						"ruby on rails",
						"postgresql",
						"heroku",
						"html",
						"css"
					],
					"time_end": "September 2016",
					"time_start": "August 2014"
				},
				{
					"additional_info": "gigatronshop.com / comtradeshop.com",
					"company": "Gigatron/ComTrade",
					"id": "67b02735-2e4a-4f66-9fed-a67e62a751aa",
					"job_title": "Web administrator",
					"time_end": "2014",
					"time_start": "2013"
				},
				{
					"additional_info": "dpa.com",
					"company": "DPA (Deutsche Presse-Agentur)",
					"id": "a57fc4e0-ff30-43b3-a031-2eff4c3bdb05",
					"job_title": "System/Network Administrator",
					"time_end": "2012",
					"time_start": "2003"
				}
			],
			"id": "fed029fa-ff24-456c-82f1-b8a088553561",
			"title": "Experience",
			"type": "experience"
		},
		"hobbies": {
			"category": "aside",
			"content": {
				"data": [
					"Guitar and music",
					"Running",
					"Gadgets",
					"History doq",
					"Diving",
					"Travel"
				],
				"type": "list"
			},
			"id": "0aad30d2-c7f4-40ed-9a09-ce52e01b6350",
			"title": "Hobbies",
			"type": "hobbies"
		},
		"interests": {
			"category": "aside",
			"content": {
				"data": [
					"React",
					"Redux",
					"Vue",
					"GraphQL",
					"Serverless",
					"Firebase",
					"Next",
					"Node",
					"MongoDB",
					"Flutter"
				],
				"type": "list"
			},
			"id": "1007989c-286e-45a9-8d35-843db4b20459",
			"title": "Interests",
			"type": "interests"
		},
		"profile": {
			"category": "aside",
			"content": {
				"data": "I am a passionate web developer with seven years of experience developing web, and history in networking and architecture. Direct and honest communication and reliability are my most prominent traits. I am very excited about improving my tech skills, learning the latest tricks of the trade, and discovering tools that could save time and provide new ways to solve old problems. My biggest asset would be my inclination to re-evaluate specific alternatives, share knowledge and expertise while spraying positive mood to strengthening cooperation inside the team.",
				"type": "text"
			},
			"id": "2c56dcb3-fed1-41f7-b319-b1fe86b759ac",
			"title": "Profile",
			"type": "profile"
		},
		"projects": {
			"category": "main",
			"content": [
				{
					"id": "d7dff661-5b1a-4aab-85fd-1fa0901cdb18",
					"technologies": [
						"react",
						"redux",
						"google firebase",
						"node",
						"cloud functions"
					],
					"title": "admin.kreativnakockica.rs",
					"url": "https://kreativna-kockica-admin-e8306.web.app/",
					"year": 2019
				},
				{
					"id": "e869881a-3365-4b6f-b34e-edf8d36331dd",
					"technologies": ["react", "redux", "bootstrap"],
					"title": "rekreativa.rs",
					"year": 2018
				},
				{
					"id": "ccf519f0-410e-4f5a-be4c-6f6f52241ea2",
					"title": "ian.org.rs",
					"url": "https://ian.org.rs/",
					"year": 2017
				},
				{
					"id": "6e302f08-b7fe-4ce2-9747-fee061553f44",
					"title": "alekkscouting.com",
					"url": "https://www.alekkscouting.com/",
					"year": 2017
				},
				{
					"id": "37088019-d4f6-4ee0-a635-3835bd9f67b6",
					"technologies": ["php", "wordpress", "jquery"],
					"title": "salakraljica.rs",
					"year": 2017
				},
				{
					"id": "5b740920-263e-42dc-9953-6bcee7c033c8",
					"title": "enjoythassos.gr",
					"year": 2016
				},
				{
					"id": "8d62da49-ce22-4da9-8b78-b58f387b88ec",
					"technologies": ["php", "wordpress", "jquery"],
					"title": "thassosing.com",
					"url": "http://www.thassosing.com/",
					"year": 2016
				}
			],
			"id": "2068c0a5-ed09-464b-98ab-da595c799da7",
			"title": "Side projects",
			"type": "projects"
		}
	}
}
